pyIOT/Component.py
pyIOT/Thing.py
pyIOT/__init__.py
pyIOT-0.1.1.dist-info/METADATA
pyIOT-0.1.1.dist-info/RECORD
pyIOT-0.1.1.dist-info/WHEEL
pyIOT-0.1.1.dist-info/top_level.txt
tests/Component_test.py
tests/Thing_test.py
tests/__init__.py
tests/example.py
tests/simulator.py
