Metadata-Version: 2.1
Name: pyIOT
Version: 0.1.1
Summary: Simplifies driver development for Amazon's IOT-Core service
Home-page: https://github.com/dhrone/pyIOT
Author: dhrone
Author-email: ron@ritchey.org
License: UNKNOWN
Platform: UNKNOWN
Classifier: Development Status :: 3 - Alpha
Classifier: Intended Audience :: Developers
Classifier: Topic :: Software Development :: Embedded Systems
Classifier: Programming Language :: Python :: 3
Classifier: License :: OSI Approved :: MIT License
Classifier: Operating System :: OS Independent
Requires-Dist: pyserial
Requires-Dist: awsiotpythonsdk
